[{
		"Name": "Dr. Ashok Seth",
		"Availability": "PM",
		"evening count": 5
	},
	{
		"Name": "Dr. Ajay Kaul",
		"Availability": "Both",
		"morning count": 5,
		"evening count": 5
	},
	{
		"Name": "Dr. Ram Kumar",
		"Availability": "PM",
		"evening count": 5
	},
	{
		"Name": "Dr. Ramesh Iyer",
		"Availability": "Both",
		"morning count": 5,
		"evening count": 5
	},
	{
		"Name": "Dr. Veena Bhat",
		"Availability": "AM",
		"morning count": 5
	},
	{
		"Name": "Dr. Aparna Santhanam",
		"Availability": "AM",
		"morning count": 5
	},
	{
		"Name": "Dr. Naresh Bhat",
		"Availability": "Both",
		"morning count": 5,
		"evening count": 5
	},
	{
		"Name": "Dr. Amitabha Ghosh",
		"Availability": "PM",
		"evening count": 5
	}


]
